mvl/__init__.py
mvl/bochvar.py
mvl/goedel.py
mvl/kleene.py
mvl/lukasiewicz.py
mvl/post.py
mvl/priest.py
mvl/product.py
mvl/tvl_operators.py
mvl/types.py
test/__init__.py
test/test_nvl.py
test/test_tvl.py
mvl-0.2.0.dist-info/LICENSE.txt
mvl-0.2.0.dist-info/METADATA
mvl-0.2.0.dist-info/WHEEL
mvl-0.2.0.dist-info/top_level.txt
mvl-0.2.0.dist-info/RECORD
