Metadata-Version: 2.1
Name: mvl
Version: 0.2.0
Summary: A package which implements various systems of n valued logic.
Home-page: https://github.com/andrewjunyoung/mvl
Author: Andrew J. Young
Author-email: andrewjunyoung1@gmail.com
License: UNKNOWN
Platform: UNKNOWN
Classifier: Programming Language :: Python :: 3
Classifier: Operating System :: OS Independent
Classifier: License :: Public Domain
Requires-Python: >=3.6
